README.md
setup.py
domaintools/__init__.py
domaintools/build_data_file.py
domaintools/data.py
domaintools/tests.py
domaintools.egg-info/PKG-INFO
domaintools.egg-info/SOURCES.txt
domaintools.egg-info/dependency_links.txt
domaintools.egg-info/top_level.txt