Metadata-Version: 1.0
Name: domaintools
Version: 0.3.8
Summary: Domain parsing with python
Home-page: http://github.com/devhub/domaintools
Author: DevHub
Author-email: UNKNOWN
License: UNKNOWN
Platform: UNKNOWN
